LICENSE
README.md
iconvcodec.py
iconvmodule.c
setup.py
python_iconv.egg-info/PKG-INFO
python_iconv.egg-info/SOURCES.txt
python_iconv.egg-info/dependency_links.txt
python_iconv.egg-info/top_level.txt