Metadata-Version: 1.0
Name: python-iconv
Version: 1.1.1
Summary: iconv-based Unicode converter
Home-page: https://github.com/bodograumann/python-iconv
Author: Bodo Graumann
Author-email: mail@bodograumann.de
License: UNKNOWN
Platform: UNKNOWN
